{
  "document_id": "D…ônizk…ônarńĪ Bulvar IŐádar…ôsinin f…ôaliyy…ôtinin t…ômin edilm…ôsi haqqńĪnda",
  "title": "D…ônizk…ônarńĪ Bulvar IŐádar…ôsinin f…ôaliyy…ôtinin t…ômin edilm…ôsi haqqńĪnda",
  "category": "payments_and_banking_operations",
  "source_file": "D…ônizk…ônarńĪ Bulvar IŐádar…ôsinin f…ôaliyy…ôtinin t…ômin edilm…ôsi haqqńĪnda.pdf",
  "processed_file": "D…ônizk…ônarńĪ Bulvar IŐádar…ôsinin f…ôaliyy…ôtinin t…ômin edilm…ôsi haqqńĪnda.md",
  "total_pages": 33,
  "total_chunks": 79,
  "language": "az",
  "parser": "pdfplumber",
  "created_at": "2026-06-27T02:46:34.049474"
}